codemelli/__init__.py
codemelli/codemelli.py
codemelli/data/code-city.json
codemelli-0.1.2.dist-info/AUTHORS.md
codemelli-0.1.2.dist-info/LICENSE
codemelli-0.1.2.dist-info/METADATA
codemelli-0.1.2.dist-info/WHEEL
codemelli-0.1.2.dist-info/top_level.txt
codemelli-0.1.2.dist-info/RECORD
