Metadata-Version: 2.1
Name: codemelli
Version: 0.1.2
Summary: Python package to validate/generate iranian national ID
Home-page: https://github.com/hanifbirgani/codemelli
Author: Hanif Birgani
License: MIT license
Keywords: codemelli
Platform: UNKNOWN
Classifier: Development Status :: 2 - Pre-Alpha
Classifier: Intended Audience :: Developers
Classifier: License :: OSI Approved :: MIT License
Classifier: Natural Language :: English
Classifier: Programming Language :: Python :: 3
Classifier: Programming Language :: Python :: 3.7
Classifier: Programming Language :: Python :: 3.8
Classifier: Programming Language :: Python :: 3.9
Requires-Python: >=3.6
License-File: LICENSE
License-File: AUTHORS.md
